Workbook

Sheet Dashboard
B2: B U D G E T T R A C K E R
B4: Year | D4: Month (1-12) | F4: Showing | J4: Year and Month start on today's date. Type over them to look at another period.
B5: =YEAR(TODAY()) | D5: =MONTH(TODAY()) | F5: =IF(OR(NOT(ISNUMBER(B5)),NOT(ISNUMBER(D5))),"Pick a year and a month",IF(OR(B5<2000,B5>2100,B5<>INT(B5)),"Pick a year 2000-2100",IF(OR(D5<1,D5>12,D5<>INT(D5)),"Pick a month 1-12",DATE(B5,D5,1)))) | J5: =IF(OR(COUNTIF(Summary!$B$20:$M$20,"<>0")>0,Summary!$B$21<>0),"Some amounts are not being counted: see the checks under the totals on the Summary tab.","Log spending on the Transactions tab and set budgets on the Budget tab.")
B7: T H I S M O N T H | J7: T H I S Y E A R
B8: Income | D8: Spent | F8: Left to spend | H8: Net saved | J8: Income | L8: Spent | N8: Saved | P8: Savings rate
B9: =Summary!$S$18 | D9: =Summary!$S$17 | F9: =Summary!$T$17 | H9: =Summary!$S$19 | J9: =Summary!$N$18 | L9: =Summary!$N$17 | N9: =Summary!$N$19 | P9: =IF(Summary!$N$18<=0,"-",Summary!$N$19/Summary!$N$18)
B12: Budget vs actual by category | J12: Income vs spending by month
B30: Category detail | J30: Spending by category this year
B31: Category | D31: Budget | F31: Spent | H31: Left
B32: =Summary!A2 | D32: =Summary!R2 | F32: =Summary!S2 | H32: =Summary!T2
B33: =Summary!A3 | D33: =Summary!R3 | F33: =Summary!S3 | H33: =Summary!T3
B34: =Summary!A4 | D34: =Summary!R4 | F34: =Summary!S4 | H34: =Summary!T4
B35: =Summary!A5 | D35: =Summary!R5 | F35: =Summary!S5 | H35: =Summary!T5
B36: =Summary!A6 | D36: =Summary!R6 | F36: =Summary!S6 | H36: =Summary!T6
B37: =Summary!A7 | D37: =Summary!R7 | F37: =Summary!S7 | H37: =Summary!T7
B38: =Summary!A8 | D38: =Summary!R8 | F38: =Summary!S8 | H38: =Summary!T8
B39: =Summary!A9 | D39: =Summary!R9 | F39: =Summary!S9 | H39: =Summary!T9
B40: =Summary!A10 | D40: =Summary!R10 | F40: =Summary!S10 | H40: =Summary!T10
B41: =Summary!A11 | D41: =Summary!R11 | F41: =Summary!S11 | H41: =Summary!T11
B42: =Summary!A12 | D42: =Summary!R12 | F42: =Summary!S12 | H42: =Summary!T12
B43: =Summary!A13 | D43: =Summary!R13 | F43: =Summary!S13 | H43: =Summary!T13
B44: Total | D44: =SUM(D32:D43) | F44: =SUM(F32:F43) | H44: =ROUND(D44-F44,2)

Sheet Transactions
A1: Date | B1: Description | C1: Category | D1: Amount | E1: Notes | G1: Tip: pick the Category from the dropdown and type amounts as positive numbers. Rows marked 'sample' are examples - delete them when you start.
A2: 46235 | B2: Paycheck | C2: Salary | D2: 2100 | E2: sample - delete me
A3: 46235 | B3: Rent | C3: Housing | D3: 1500 | E3: sample - delete me
A4: 46237 | B4: Supermarket | C4: Groceries | D4: 142.35 | E4: sample - delete me
A5: 46239 | B5: Electricity & water | C5: Utilities | D5: 118.4 | E5: sample - delete me
A6: 46242 | B6: Gas station | C6: Transportation | D6: 64.3 | E6: sample - delete me
A7: 46243 | B7: Dinner out | C7: Dining Out | D7: 72.5 | E7: sample - delete me
A8: 46244 | B8: Supermarket | C8: Groceries | D8: 128.9 | E8: sample - delete me
A9: 46246 | B9: Internet & phone | C9: Utilities | D9: 85 | E9: sample - delete me
A10: 46248 | B10: Car insurance | C10: Insurance | D10: 180 | E10: sample - delete me
A11: 46249 | B11: Paycheck | C11: Salary | D11: 2100 | E11: sample - delete me
A12: 46251 | B12: Supermarket | C12: Groceries | D12: 156.2 | E12: sample - delete me
A13: 46253 | B13: Concert tickets | C13: Entertainment | D13: 95 | E13: sample - delete me
... A44: 46299 | B44: Coffee shop | C44: Dining Out | D44: 12.4 | E44: sample - delete me

Sheet Budget
A1: Category | B1: Type | C1: Monthly Budget | D1: Yearly Budget | F1: How to use
A2: Housing | B2: Expense | C2: 1500 | D2: =C2*12 | F2: Yellow cells are yours to edit: category names and monthly budgets.
A3: Utilities | B3: Expense | C3: 220 | D3: =C3*12 | F3: Rows 2-13 are spending categories and rows 14-15 are income; the row decides, Type is just a label.
A4: Groceries | B4: Expense | C4: 600 | D4: =C4*12 | F4: Rename categories freely, but keep names unique and don't insert or delete rows.
A5: Dining Out | B5: Expense | C5: 200 | D5: =C5*12 | F5: Avoid the characters * ? ~ in names (spreadsheets treat them as wildcards).
A6: Transportation | B6: Expense | C6: 250 | D6: =C6*12 | F6: Renaming a category here also renames it in the Transactions dropdown,
A7: Insurance | B7: Expense | C7: 180 | D7: =C7*12 | F7: but transactions already logged under the old name must be re-picked.
A8: Health | B8: Expense | C8: 100 | D8: =C8*12 | F8: Transactions tab: one row per purchase or paycheck, amounts as positive numbers.
A9: Subscriptions | B9: Expense | C9: 60 | D9: =C9*12 | F9: The Category decides whether a row counts as income or spending; enter a refund as a negative amount.
A10: Shopping | B10: Expense | C10: 150 | D10: =C10*12 | F10: If you log card purchases one by one, don't also log the card bill: it would count twice.
A11: Entertainment | B11: Expense | C11: 120 | D11: =C11*12
A12: Debt Payments | B12: Expense | C12: 300 | D12: =C12*12
A13: Miscellaneous | B13: Expense | C13: 100 | D13: =C13*12
A14: Salary | B14: Income | C14: 4200 | D14: =C14*12
A15: Other Income | B15: Income | C15: 200 | D15: =C15*12
A17: Total expenses | C17: =SUM(C2:C13) | D17: =SUM(D2:D13)
A18: Total income | C18: =SUM(C14:C15) | D18: =SUM(D14:D15)
A19: Planned savings | C19: =ROUND(C18-C17,2) | D19: =ROUND(D18-D17,2)

Sheet Summary
A1: ="Category ("&Dashboard!$B$5&")" | B1: Jan | C1: Feb | D1: Mar | E1: Apr | F1: May | G1: Jun | H1: Jul | I1: Aug | J1: Sep | K1: Oct | L1: Nov | M1: Dec | N1: Year Actual | O1: Year Budget | P1: Year Left | Q1: % of Budget | R1: Month Budget | S1: Month Actual | T1: Month Left | U1: Match key
A2: =IF(Budget!A2="","(unused)",Budget!A2) | B2: =SUMIFS(Transactions!$D:$D,Transactions!$C:$C,$U2,Transactions!$A:$A,">="&DATE(Dashboard!$B$5,1,1),Transactions!$A:$A,"<"&DATE(Dashboard!$B$5,2,1)) | C2: =SUMIFS(Transactions!$D:$D,Transactions!$C:$C,$U2,Transactions!$A:$A,">="&DATE(Dashboard!$B$5,2,1),Transactions!$A:$A,"<"&DATE(Dashboard!$B$5,3,1)) | D2: =SUMIFS(Transactions!$D:$D,Transactions!$C:$C,$U2,Transactions!$A:$A,">="&DATE(Dashboard!$B$5,3,1),Transactions!$A:$A,"<"&DATE(Dashboard!$B$5,4,1)) | E2: =SUMIFS(Transactions!$D:$D,Transactions!$C:$C,$U2,Transactions!$A:$A,">="&DATE(Dashboard!$B$5,4,1),Transactions!$A:$A,"<"&DATE(Dashboard!$B$5,5,1)) | F2: =SUMIFS(Transactions!$D:$D,Transactions!$C:$C,$U2,Transactions!$A:$A,">="&DATE(Dashboard!$B$5,5,1),Transactions!$A:$A,"<"&DATE(Dashboard!$B$5,6,1)) | G2: =SUMIFS(Transactions!$D:$D,Transactions!$C:$C,$U2,Transactions!$A:$A,">="&DATE(Dashboard!$B$5,6,1),Transactions!$A:$A,"<"&DATE(Dashboard!$B$5,7,1)) | H2: =SUMIFS(Transactions!$D:$D,Transactions!$C:$C,$U2,Transactions!$A:$A,">="&DATE(Dashboard!$B$5,7,1),Transactions!$A:$A,"<"&DATE(Dashboard!$B$5,8,1)) | I2: =SUMIFS(Transactions!$D:$D,Transactions!$C:$C,$U2,Transactions!$A:$A,">="&DATE(Dashboard!$B$5,8,1),Transactions!$A:$A,"<"&DATE(Dashboard!$B$5,9,1)) | J2: =SUMIFS(Transactions!$D:$D,Transactions!$C:$C,$U2,Transactions!$A:$A,">="&DATE(Dashboard!$B$5,9,1),Transactions!$A:$A,"<"&DATE(Dashboard!$B$5,10,1)) | K2: =SUMIFS(Transactions!$D:$D,Transactions!$C:$C,$U2,Transactions!$A:$A,">="&DATE(Dashboard!$B$5,10,1),Transactions!$A:$A,"<"&DATE(Dashboard!$B$5,11,1)) | L2: =SUMIFS(Transactions!$D:$D,Transactions!$C:$C,$U2,Transactions!$A:$A,">="&DATE(Dashboard!$B$5,11,1),Transactions!$A:$A,"<"&DATE(Dashboard!$B$5,12,1)) | M2: =SUMIFS(Transactions!$D:$D,Transactions!$C:$C,$U2,Transactions!$A:$A,">="&DATE(Dashboard!$B$5,12,1),Transactions!$A:$A,"<"&DATE(Dashboard!$B$5,13,1)) | N2: =SUM(B2:M2) | O2: =Budget!D2 | P2: =ROUND(O2-N2,2) | Q2: =IF(O2=0,"",N2/O2) | R2: =Budget!C2 | S2: =IF(ISNUMBER(Dashboard!$F$5),INDEX(B2:M2,1,MONTH(Dashboard!$F$5)),0) | T2: =ROUND(R2-S2,2) | U2: =SUBSTITUTE(SUBSTITUTE(SUBSTITUTE($A2,"~","~~"),"*","~*"),"?","~?")
A3: =IF(Budget!A3="","(unused)",Budget!A3) | B3: =SUMIFS(Transactions!$D:$D,Transactions!$C:$C,$U3,Transactions!$A:$A,">="&DATE(Dashboard!$B$5,1,1),Transactions!$A:$A,"<"&DATE(Dashboard!$B$5,2,1)) | C3: =SUMIFS(Transactions!$D:$D,Transactions!$C:$C,$U3,Transactions!$A:$A,">="&DATE(Dashboard!$B$5,2,1),Transactions!$A:$A,"<"&DATE(Dashboard!$B$5,3,1)) | D3: =SUMIFS(Transactions!$D:$D,Transactions!$C:$C,$U3,Transactions!$A:$A,">="&DATE(Dashboard!$B$5,3,1),Transactions!$A:$A,"<"&DATE(Dashboard!$B$5,4,1)) | E3: =SUMIFS(Transactions!$D:$D,Transactions!$C:$C,$U3,Transactions!$A:$A,">="&DATE(Dashboard!$B$5,4,1),Transactions!$A:$A,"<"&DATE(Dashboard!$B$5,5,1)) | F3: =SUMIFS(Transactions!$D:$D,Transactions!$C:$C,$U3,Transactions!$A:$A,">="&DATE(Dashboard!$B$5,5,1),Transactions!$A:$A,"<"&DATE(Dashboard!$B$5,6,1)) | G3: =SUMIFS(Transactions!$D:$D,Transactions!$C:$C,$U3,Transactions!$A:$A,">="&DATE(Dashboard!$B$5,6,1),Transactions!$A:$A,"<"&DATE(Dashboard!$B$5,7,1)) | H3: =SUMIFS(Transactions!$D:$D,Transactions!$C:$C,$U3,Transactions!$A:$A,">="&DATE(Dashboard!$B$5,7,1),Transactions!$A:$A,"<"&DATE(Dashboard!$B$5,8,1)) | I3: =SUMIFS(Transactions!$D:$D,Transactions!$C:$C,$U3,Transactions!$A:$A,">="&DATE(Dashboard!$B$5,8,1),Transactions!$A:$A,"<"&DATE(Dashboard!$B$5,9,1)) | J3: =SUMIFS(Transactions!$D:$D,Transactions!$C:$C,$U3,Transactions!$A:$A,">="&DATE(Dashboard!$B$5,9,1),Transactions!$A:$A,"<"&DATE(Dashboard!$B$5,10,1)) | K3: =SUMIFS(Transactions!$D:$D,Transactions!$C:$C,$U3,Transactions!$A:$A,">="&DATE(Dashboard!$B$5,10,1),Transactions!$A:$A,"<"&DATE(Dashboard!$B$5,11,1)) | L3: =SUMIFS(Transactions!$D:$D,Transactions!$C:$C,$U3,Transactions!$A:$A,">="&DATE(Dashboard!$B$5,11,1),Transactions!$A:$A,"<"&DATE(Dashboard!$B$5,12,1)) | M3: =SUMIFS(Transactions!$D:$D,Transactions!$C:$C,$U3,Transactions!$A:$A,">="&DATE(Dashboard!$B$5,12,1),Transactions!$A:$A,"<"&DATE(Dashboard!$B$5,13,1)) | N3: =SUM(B3:M3) | O3: =Budget!D3 | P3: =ROUND(O3-N3,2) | Q3: =IF(O3=0,"",N3/O3) | R3: =Budget!C3 | S3: =IF(ISNUMBER(Dashboard!$F$5),INDEX(B3:M3,1,MONTH(Dashboard!$F$5)),0) | T3: =ROUND(R3-S3,2) | U3: =SUBSTITUTE(SUBSTITUTE(SUBSTITUTE($A3,"~","~~"),"*","~*"),"?","~?")
A4: =IF(Budget!A4="","(unused)",Budget!A4) | B4: =SUMIFS(Transactions!$D:$D,Transactions!$C:$C,$U4,Transactions!$A:$A,">="&DATE(Dashboard!$B$5,1,1),Transactions!$A:$A,"<"&DATE(Dashboard!$B$5,2,1)) | C4: =SUMIFS(Transactions!$D:$D,Transactions!$C:$C,$U4,Transactions!$A:$A,">="&DATE(Dashboard!$B$5,2,1),Transactions!$A:$A,"<"&DATE(Dashboard!$B$5,3,1)) | D4: =SUMIFS(Transactions!$D:$D,Transactions!$C:$C,$U4,Transactions!$A:$A,">="&DATE(Dashboard!$B$5,3,1),Transactions!$A:$A,"<"&DATE(Dashboard!$B$5,4,1)) | E4: =SUMIFS(Transactions!$D:$D,Transactions!$C:$C,$U4,Transactions!$A:$A,">="&DATE(Dashboard!$B$5,4,1),Transactions!$A:$A,"<"&DATE(Dashboard!$B$5,5,1)) | F4: =SUMIFS(Transactions!$D:$D,Transactions!$C:$C,$U4,Transactions!$A:$A,">="&DATE(Dashboard!$B$5,5,1),Transactions!$A:$A,"<"&DATE(Dashboard!$B$5,6,1)) | G4: =SUMIFS(Transactions!$D:$D,Transactions!$C:$C,$U4,Transactions!$A:$A,">="&DATE(Dashboard!$B$5,6,1),Transactions!$A:$A,"<"&DATE(Dashboard!$B$5,7,1)) | H4: =SUMIFS(Transactions!$D:$D,Transactions!$C:$C,$U4,Transactions!$A:$A,">="&DATE(Dashboard!$B$5,7,1),Transactions!$A:$A,"<"&DATE(Dashboard!$B$5,8,1)) | I4: =SUMIFS(Transactions!$D:$D,Transactions!$C:$C,$U4,Transactions!$A:$A,">="&DATE(Dashboard!$B$5,8,1),Transactions!$A:$A,"<"&DATE(Dashboard!$B$5,9,1)) | J4: =SUMIFS(Transactions!$D:$D,Transactions!$C:$C,$U4,Transactions!$A:$A,">="&DATE(Dashboard!$B$5,9,1),Transactions!$A:$A,"<"&DATE(Dashboard!$B$5,10,1)) | K4: =SUMIFS(Transactions!$D:$D,Transactions!$C:$C,$U4,Transactions!$A:$A,">="&DATE(Dashboard!$B$5,10,1),Transactions!$A:$A,"<"&DATE(Dashboard!$B$5,11,1)) | L4: =SUMIFS(Transactions!$D:$D,Transactions!$C:$C,$U4,Transactions!$A:$A,">="&DATE(Dashboard!$B$5,11,1),Transactions!$A:$A,"<"&DATE(Dashboard!$B$5,12,1)) | M4: =SUMIFS(Transactions!$D:$D,Transactions!$C:$C,$U4,Transactions!$A:$A,">="&DATE(Dashboard!$B$5,12,1),Transactions!$A:$A,"<"&DATE(Dashboard!$B$5,13,1)) | N4: =SUM(B4:M4) | O4: =Budget!D4 | P4: =ROUND(O4-N4,2) | Q4: =IF(O4=0,"",N4/O4) | R4: =Budget!C4 | S4: =IF(ISNUMBER(Dashboard!$F$5),INDEX(B4:M4,1,MONTH(Dashboard!$F$5)),0) | T4: =ROUND(R4-S4,2) | U4: =SUBSTITUTE(SUBSTITUTE(SUBSTITUTE($A4,"~","~~"),"*","~*"),"?","~?")
A5: =IF(Budget!A5="","(unused)",Budget!A5) | B5: =SUMIFS(Transactions!$D:$D,Transactions!$C:$C,$U5,Transactions!$A:$A,">="&DATE(Dashboard!$B$5,1,1),Transactions!$A:$A,"<"&DATE(Dashboard!$B$5,2,1)) | C5: =SUMIFS(Transactions!$D:$D,Transactions!$C:$C,$U5,Transactions!$A:$A,">="&DATE(Dashboard!$B$5,2,1),Transactions!$A:$A,"<"&DATE(Dashboard!$B$5,3,1)) | D5: =SUMIFS(Transactions!$D:$D,Transactions!$C:$C,$U5,Transactions!$A:$A,">="&DATE(Dashboard!$B$5,3,1),Transactions!$A:$A,"<"&DATE(Dashboard!$B$5,4,1)) | E5: =SUMIFS(Transactions!$D:$D,Transactions!$C:$C,$U5,Transactions!$A:$A,">="&DATE(Dashboard!$B$5,4,1),Transactions!$A:$A,"<"&DATE(Dashboard!$B$5,5,1)) | F5: =SUMIFS(Transactions!$D:$D,Transactions!$C:$C,$U5,Transactions!$A:$A,">="&DATE(Dashboard!$B$5,5,1),Transactions!$A:$A,"<"&DATE(Dashboard!$B$5,6,1)) | G5: =SUMIFS(Transactions!$D:$D,Transactions!$C:$C,$U5,Transactions!$A:$A,">="&DATE(Dashboard!$B$5,6,1),Transactions!$A:$A,"<"&DATE(Dashboard!$B$5,7,1)) | H5: =SUMIFS(Transactions!$D:$D,Transactions!$C:$C,$U5,Transactions!$A:$A,">="&DATE(Dashboard!$B$5,7,1),Transactions!$A:$A,"<"&DATE(Dashboard!$B$5,8,1)) | I5: =SUMIFS(Transactions!$D:$D,Transactions!$C:$C,$U5,Transactions!$A:$A,">="&DATE(Dashboard!$B$5,8,1),Transactions!$A:$A,"<"&DATE(Dashboard!$B$5,9,1)) | J5: =SUMIFS(Transactions!$D:$D,Transactions!$C:$C,$U5,Transactions!$A:$A,">="&DATE(Dashboard!$B$5,9,1),Transactions!$A:$A,"<"&DATE(Dashboard!$B$5,10,1)) | K5: =SUMIFS(Transactions!$D:$D,Transactions!$C:$C,$U5,Transactions!$A:$A,">="&DATE(Dashboard!$B$5,10,1),Transactions!$A:$A,"<"&DATE(Dashboard!$B$5,11,1)) | L5: =SUMIFS(Transactions!$D:$D,Transactions!$C:$C,$U5,Transactions!$A:$A,">="&DATE(Dashboard!$B$5,11,1),Transactions!$A:$A,"<"&DATE(Dashboard!$B$5,12,1)) | M5: =SUMIFS(Transactions!$D:$D,Transactions!$C:$C,$U5,Transactions!$A:$A,">="&DATE(Dashboard!$B$5,12,1),Transactions!$A:$A,"<"&DATE(Dashboard!$B$5,13,1)) | N5: =SUM(B5:M5) | O5: =Budget!D5 | P5: =ROUND(O5-N5,2) | Q5: =IF(O5=0,"",N5/O5) | R5: =Budget!C5 | S5: =IF(ISNUMBER(Dashboard!$F$5),INDEX(B5:M5,1,MONTH(Dashboard!$F$5)),0) | T5: =ROUND(R5-S5,2) | U5: =SUBSTITUTE(SUBSTITUTE(SUBSTITUTE($A5,"~","~~"),"*","~*"),"?","~?")
A6: =IF(Budget!A6="","(unused)",Budget!A6) | B6: =SUMIFS(Transactions!$D:$D,Transactions!$C:$C,$U6,Transactions!$A:$A,">="&DATE(Dashboard!$B$5,1,1),Transactions!$A:$A,"<"&DATE(Dashboard!$B$5,2,1)) | C6: =SUMIFS(Transactions!$D:$D,Transactions!$C:$C,$U6,Transactions!$A:$A,">="&DATE(Dashboard!$B$5,2,1),Transactions!$A:$A,"<"&DATE(Dashboard!$B$5,3,1)) | D6: =SUMIFS(Transactions!$D:$D,Transactions!$C:$C,$U6,Transactions!$A:$A,">="&DATE(Dashboard!$B$5,3,1),Transactions!$A:$A,"<"&DATE(Dashboard!$B$5,4,1)) | E6: =SUMIFS(Transactions!$D:$D,Transactions!$C:$C,$U6,Transactions!$A:$A,">="&DATE(Dashboard!$B$5,4,1),Transactions!$A:$A,"<"&DATE(Dashboard!$B$5,5,1)) | F6: =SUMIFS(Transactions!$D:$D,Transactions!$C:$C,$U6,Transactions!$A:$A,">="&DATE(Dashboard!$B$5,5,1),Transactions!$A:$A,"<"&DATE(Dashboard!$B$5,6,1)) | G6: =SUMIFS(Transactions!$D:$D,Transactions!$C:$C,$U6,Transactions!$A:$A,">="&DATE(Dashboard!$B$5,6,1),Transactions!$A:$A,"<"&DATE(Dashboard!$B$5,7,1)) | H6: =SUMIFS(Transactions!$D:$D,Transactions!$C:$C,$U6,Transactions!$A:$A,">="&DATE(Dashboard!$B$5,7,1),Transactions!$A:$A,"<"&DATE(Dashboard!$B$5,8,1)) | I6: =SUMIFS(Transactions!$D:$D,Transactions!$C:$C,$U6,Transactions!$A:$A,">="&DATE(Dashboard!$B$5,8,1),Transactions!$A:$A,"<"&DATE(Dashboard!$B$5,9,1)) | J6: =SUMIFS(Transactions!$D:$D,Transactions!$C:$C,$U6,Transactions!$A:$A,">="&DATE(Dashboard!$B$5,9,1),Transactions!$A:$A,"<"&DATE(Dashboard!$B$5,10,1)) | K6: =SUMIFS(Transactions!$D:$D,Transactions!$C:$C,$U6,Transactions!$A:$A,">="&DATE(Dashboard!$B$5,10,1),Transactions!$A:$A,"<"&DATE(Dashboard!$B$5,11,1)) | L6: =SUMIFS(Transactions!$D:$D,Transactions!$C:$C,$U6,Transactions!$A:$A,">="&DATE(Dashboard!$B$5,11,1),Transactions!$A:$A,"<"&DATE(Dashboard!$B$5,12,1)) | M6: =SUMIFS(Transactions!$D:$D,Transactions!$C:$C,$U6,Transactions!$A:$A,">="&DATE(Dashboard!$B$5,12,1),Transactions!$A:$A,"<"&DATE(Dashboard!$B$5,13,1)) | N6: =SUM(B6:M6) | O6: =Budget!D6 | P6: =ROUND(O6-N6,2) | Q6: =IF(O6=0,"",N6/O6) | R6: =Budget!C6 | S6: =IF(ISNUMBER(Dashboard!$F$5),INDEX(B6:M6,1,MONTH(Dashboard!$F$5)),0) | T6: =ROUND(R6-S6,2) | U6: =SUBSTITUTE(SUBSTITUTE(SUBSTITUTE($A6,"~","~~"),"*","~*"),"?","~?")
A7: =IF(Budget!A7="","(unused)",Budget!A7) | B7: =SUMIFS(Transactions!$D:$D,Transactions!$C:$C,$U7,Transactions!$A:$A,">="&DATE(Dashboard!$B$5,1,1),Transactions!$A:$A,"<"&DATE(Dashboard!$B$5,2,1)) | C7: =SUMIFS(Transactions!$D:$D,Transactions!$C:$C,$U7,Transactions!$A:$A,">="&DATE(Dashboard!$B$5,2,1),Transactions!$A:$A,"<"&DATE(Dashboard!$B$5,3,1)) | D7: =SUMIFS(Transactions!$D:$D,Transactions!$C:$C,$U7,Transactions!$A:$A,">="&DATE(Dashboard!$B$5,3,1),Transactions!$A:$A,"<"&DATE(Dashboard!$B$5,4,1)) | E7: =SUMIFS(Transactions!$D:$D,Transactions!$C:$C,$U7,Transactions!$A:$A,">="&DATE(Dashboard!$B$5,4,1),Transactions!$A:$A,"<"&DATE(Dashboard!$B$5,5,1)) | F7: =SUMIFS(Transactions!$D:$D,Transactions!$C:$C,$U7,Transactions!$A:$A,">="&DATE(Dashboard!$B$5,5,1),Transactions!$A:$A,"<"&DATE(Dashboard!$B$5,6,1)) | G7: =SUMIFS(Transactions!$D:$D,Transactions!$C:$C,$U7,Transactions!$A:$A,">="&DATE(Dashboard!$B$5,6,1),Transactions!$A:$A,"<"&DATE(Dashboard!$B$5,7,1)) | H7: =SUMIFS(Transactions!$D:$D,Transactions!$C:$C,$U7,Transactions!$A:$A,">="&DATE(Dashboard!$B$5,7,1),Transactions!$A:$A,"<"&DATE(Dashboard!$B$5,8,1)) | I7: =SUMIFS(Transactions!$D:$D,Transactions!$C:$C,$U7,Transactions!$A:$A,">="&DATE(Dashboard!$B$5,8,1),Transactions!$A:$A,"<"&DATE(Dashboard!$B$5,9,1)) | J7: =SUMIFS(Transactions!$D:$D,Transactions!$C:$C,$U7,Transactions!$A:$A,">="&DATE(Dashboard!$B$5,9,1),Transactions!$A:$A,"<"&DATE(Dashboard!$B$5,10,1)) | K7: =SUMIFS(Transactions!$D:$D,Transactions!$C:$C,$U7,Transactions!$A:$A,">="&DATE(Dashboard!$B$5,10,1),Transactions!$A:$A,"<"&DATE(Dashboard!$B$5,11,1)) | L7: =SUMIFS(Transactions!$D:$D,Transactions!$C:$C,$U7,Transactions!$A:$A,">="&DATE(Dashboard!$B$5,11,1),Transactions!$A:$A,"<"&DATE(Dashboard!$B$5,12,1)) | M7: =SUMIFS(Transactions!$D:$D,Transactions!$C:$C,$U7,Transactions!$A:$A,">="&DATE(Dashboard!$B$5,12,1),Transactions!$A:$A,"<"&DATE(Dashboard!$B$5,13,1)) | N7: =SUM(B7:M7) | O7: =Budget!D7 | P7: =ROUND(O7-N7,2) | Q7: =IF(O7=0,"",N7/O7) | R7: =Budget!C7 | S7: =IF(ISNUMBER(Dashboard!$F$5),INDEX(B7:M7,1,MONTH(Dashboard!$F$5)),0) | T7: =ROUND(R7-S7,2) | U7: =SUBSTITUTE(SUBSTITUTE(SUBSTITUTE($A7,"~","~~"),"*","~*"),"?","~?")
A8: =IF(Budget!A8="","(unused)",Budget!A8) | B8: =SUMIFS(Transactions!$D:$D,Transactions!$C:$C,$U8,Transactions!$A:$A,">="&DATE(Dashboard!$B$5,1,1),Transactions!$A:$A,"<"&DATE(Dashboard!$B$5,2,1)) | C8: =SUMIFS(Transactions!$D:$D,Transactions!$C:$C,$U8,Transactions!$A:$A,">="&DATE(Dashboard!$B$5,2,1),Transactions!$A:$A,"<"&DATE(Dashboard!$B$5,3,1)) | D8: =SUMIFS(Transactions!$D:$D,Transactions!$C:$C,$U8,Transactions!$A:$A,">="&DATE(Dashboard!$B$5,3,1),Transactions!$A:$A,"<"&DATE(Dashboard!$B$5,4,1)) | E8: =SUMIFS(Transactions!$D:$D,Transactions!$C:$C,$U8,Transactions!$A:$A,">="&DATE(Dashboard!$B$5,4,1),Transactions!$A:$A,"<"&DATE(Dashboard!$B$5,5,1)) | F8: =SUMIFS(Transactions!$D:$D,Transactions!$C:$C,$U8,Transactions!$A:$A,">="&DATE(Dashboard!$B$5,5,1),Transactions!$A:$A,"<"&DATE(Dashboard!$B$5,6,1)) | G8: =SUMIFS(Transactions!$D:$D,Transactions!$C:$C,$U8,Transactions!$A:$A,">="&DATE(Dashboard!$B$5,6,1),Transactions!$A:$A,"<"&DATE(Dashboard!$B$5,7,1)) | H8: =SUMIFS(Transactions!$D:$D,Transactions!$C:$C,$U8,Transactions!$A:$A,">="&DATE(Dashboard!$B$5,7,1),Transactions!$A:$A,"<"&DATE(Dashboard!$B$5,8,1)) | I8: =SUMIFS(Transactions!$D:$D,Transactions!$C:$C,$U8,Transactions!$A:$A,">="&DATE(Dashboard!$B$5,8,1),Transactions!$A:$A,"<"&DATE(Dashboard!$B$5,9,1)) | J8: =SUMIFS(Transactions!$D:$D,Transactions!$C:$C,$U8,Transactions!$A:$A,">="&DATE(Dashboard!$B$5,9,1),Transactions!$A:$A,"<"&DATE(Dashboard!$B$5,10,1)) | K8: =SUMIFS(Transactions!$D:$D,Transactions!$C:$C,$U8,Transactions!$A:$A,">="&DATE(Dashboard!$B$5,10,1),Transactions!$A:$A,"<"&DATE(Dashboard!$B$5,11,1)) | L8: =SUMIFS(Transactions!$D:$D,Transactions!$C:$C,$U8,Transactions!$A:$A,">="&DATE(Dashboard!$B$5,11,1),Transactions!$A:$A,"<"&DATE(Dashboard!$B$5,12,1)) | M8: =SUMIFS(Transactions!$D:$D,Transactions!$C:$C,$U8,Transactions!$A:$A,">="&DATE(Dashboard!$B$5,12,1),Transactions!$A:$A,"<"&DATE(Dashboard!$B$5,13,1)) | N8: =SUM(B8:M8) | O8: =Budget!D8 | P8: =ROUND(O8-N8,2) | Q8: =IF(O8=0,"",N8/O8) | R8: =Budget!C8 | S8: =IF(ISNUMBER(Dashboard!$F$5),INDEX(B8:M8,1,MONTH(Dashboard!$F$5)),0) | T8: =ROUND(R8-S8,2) | U8: =SUBSTITUTE(SUBSTITUTE(SUBSTITUTE($A8,"~","~~"),"*","~*"),"?","~?")
A9: =IF(Budget!A9="","(unused)",Budget!A9) | B9: =SUMIFS(Transactions!$D:$D,Transactions!$C:$C,$U9,Transactions!$A:$A,">="&DATE(Dashboard!$B$5,1,1),Transactions!$A:$A,"<"&DATE(Dashboard!$B$5,2,1)) | C9: =SUMIFS(Transactions!$D:$D,Transactions!$C:$C,$U9,Transactions!$A:$A,">="&DATE(Dashboard!$B$5,2,1),Transactions!$A:$A,"<"&DATE(Dashboard!$B$5,3,1)) | D9: =SUMIFS(Transactions!$D:$D,Transactions!$C:$C,$U9,Transactions!$A:$A,">="&DATE(Dashboard!$B$5,3,1),Transactions!$A:$A,"<"&DATE(Dashboard!$B$5,4,1)) | E9: =SUMIFS(Transactions!$D:$D,Transactions!$C:$C,$U9,Transactions!$A:$A,">="&DATE(Dashboard!$B$5,4,1),Transactions!$A:$A,"<"&DATE(Dashboard!$B$5,5,1)) | F9: =SUMIFS(Transactions!$D:$D,Transactions!$C:$C,$U9,Transactions!$A:$A,">="&DATE(Dashboard!$B$5,5,1),Transactions!$A:$A,"<"&DATE(Dashboard!$B$5,6,1)) | G9: =SUMIFS(Transactions!$D:$D,Transactions!$C:$C,$U9,Transactions!$A:$A,">="&DATE(Dashboard!$B$5,6,1),Transactions!$A:$A,"<"&DATE(Dashboard!$B$5,7,1)) | H9: =SUMIFS(Transactions!$D:$D,Transactions!$C:$C,$U9,Transactions!$A:$A,">="&DATE(Dashboard!$B$5,7,1),Transactions!$A:$A,"<"&DATE(Dashboard!$B$5,8,1)) | I9: =SUMIFS(Transactions!$D:$D,Transactions!$C:$C,$U9,Transactions!$A:$A,">="&DATE(Dashboard!$B$5,8,1),Transactions!$A:$A,"<"&DATE(Dashboard!$B$5,9,1)) | J9: =SUMIFS(Transactions!$D:$D,Transactions!$C:$C,$U9,Transactions!$A:$A,">="&DATE(Dashboard!$B$5,9,1),Transactions!$A:$A,"<"&DATE(Dashboard!$B$5,10,1)) | K9: =SUMIFS(Transactions!$D:$D,Transactions!$C:$C,$U9,Transactions!$A:$A,">="&DATE(Dashboard!$B$5,10,1),Transactions!$A:$A,"<"&DATE(Dashboard!$B$5,11,1)) | L9: =SUMIFS(Transactions!$D:$D,Transactions!$C:$C,$U9,Transactions!$A:$A,">="&DATE(Dashboard!$B$5,11,1),Transactions!$A:$A,"<"&DATE(Dashboard!$B$5,12,1)) | M9: =SUMIFS(Transactions!$D:$D,Transactions!$C:$C,$U9,Transactions!$A:$A,">="&DATE(Dashboard!$B$5,12,1),Transactions!$A:$A,"<"&DATE(Dashboard!$B$5,13,1)) | N9: =SUM(B9:M9) | O9: =Budget!D9 | P9: =ROUND(O9-N9,2) | Q9: =IF(O9=0,"",N9/O9) | R9: =Budget!C9 | S9: =IF(ISNUMBER(Dashboard!$F$5),INDEX(B9:M9,1,MONTH(Dashboard!$F$5)),0) | T9: =ROUND(R9-S9,2) | U9: =SUBSTITUTE(SUBSTITUTE(SUBSTITUTE($A9,"~","~~"),"*","~*"),"?","~?")
A10: =IF(Budget!A10="","(unused)",Budget!A10) | B10: =SUMIFS(Transactions!$D:$D,Transactions!$C:$C,$U10,Transactions!$A:$A,">="&DATE(Dashboard!$B$5,1,1),Transactions!$A:$A,"<"&DATE(Dashboard!$B$5,2,1)) | C10: =SUMIFS(Transactions!$D:$D,Transactions!$C:$C,$U10,Transactions!$A:$A,">="&DATE(Dashboard!$B$5,2,1),Transactions!$A:$A,"<"&DATE(Dashboard!$B$5,3,1)) | D10: =SUMIFS(Transactions!$D:$D,Transactions!$C:$C,$U10,Transactions!$A:$A,">="&DATE(Dashboard!$B$5,3,1),Transactions!$A:$A,"<"&DATE(Dashboard!$B$5,4,1)) | E10: =SUMIFS(Transactions!$D:$D,Transactions!$C:$C,$U10,Transactions!$A:$A,">="&DATE(Dashboard!$B$5,4,1),Transactions!$A:$A,"<"&DATE(Dashboard!$B$5,5,1)) | F10: =SUMIFS(Transactions!$D:$D,Transactions!$C:$C,$U10,Transactions!$A:$A,">="&DATE(Dashboard!$B$5,5,1),Transactions!$A:$A,"<"&DATE(Dashboard!$B$5,6,1)) | G10: =SUMIFS(Transactions!$D:$D,Transactions!$C:$C,$U10,Transactions!$A:$A,">="&DATE(Dashboard!$B$5,6,1),Transactions!$A:$A,"<"&DATE(Dashboard!$B$5,7,1)) | H10: =SUMIFS(Transactions!$D:$D,Transactions!$C:$C,$U10,Transactions!$A:$A,">="&DATE(Dashboard!$B$5,7,1),Transactions!$A:$A,"<"&DATE(Dashboard!$B$5,8,1)) | I10: =SUMIFS(Transactions!$D:$D,Transactions!$C:$C,$U10,Transactions!$A:$A,">="&DATE(Dashboard!$B$5,8,1),Transactions!$A:$A,"<"&DATE(Dashboard!$B$5,9,1)) | J10: =SUMIFS(Transactions!$D:$D,Transactions!$C:$C,$U10,Transactions!$A:$A,">="&DATE(Dashboard!$B$5,9,1),Transactions!$A:$A,"<"&DATE(Dashboard!$B$5,10,1)) | K10: =SUMIFS(Transactions!$D:$D,Transactions!$C:$C,$U10,Transactions!$A:$A,">="&DATE(Dashboard!$B$5,10,1),Transactions!$A:$A,"<"&DATE(Dashboard!$B$5,11,1)) | L10: =SUMIFS(Transactions!$D:$D,Transactions!$C:$C,$U10,Transactions!$A:$A,">="&DATE(Dashboard!$B$5,11,1),Transactions!$A:$A,"<"&DATE(Dashboard!$B$5,12,1)) | M10: =SUMIFS(Transactions!$D:$D,Transactions!$C:$C,$U10,Transactions!$A:$A,">="&DATE(Dashboard!$B$5,12,1),Transactions!$A:$A,"<"&DATE(Dashboard!$B$5,13,1)) | N10: =SUM(B10:M10) | O10: =Budget!D10 | P10: =ROUND(O10-N10,2) | Q10: =IF(O10=0,"",N10/O10) | R10: =Budget!C10 | S10: =IF(ISNUMBER(Dashboard!$F$5),INDEX(B10:M10,1,MONTH(Dashboard!$F$5)),0) | T10: =ROUND(R10-S10,2) | U10: =SUBSTITUTE(SUBSTITUTE(SUBSTITUTE($A10,"~","~~"),"*","~*"),"?","~?")
A11: =IF(Budget!A11="","(unused)",Budget!A11) | B11: =SUMIFS(Transactions!$D:$D,Transactions!$C:$C,$U11,Transactions!$A:$A,">="&DATE(Dashboard!$B$5,1,1),Transactions!$A:$A,"<"&DATE(Dashboard!$B$5,2,1)) | C11: =SUMIFS(Transactions!$D:$D,Transactions!$C:$C,$U11,Transactions!$A:$A,">="&DATE(Dashboard!$B$5,2,1),Transactions!$A:$A,"<"&DATE(Dashboard!$B$5,3,1)) | D11: =SUMIFS(Transactions!$D:$D,Transactions!$C:$C,$U11,Transactions!$A:$A,">="&DATE(Dashboard!$B$5,3,1),Transactions!$A:$A,"<"&DATE(Dashboard!$B$5,4,1)) | E11: =SUMIFS(Transactions!$D:$D,Transactions!$C:$C,$U11,Transactions!$A:$A,">="&DATE(Dashboard!$B$5,4,1),Transactions!$A:$A,"<"&DATE(Dashboard!$B$5,5,1)) | F11: =SUMIFS(Transactions!$D:$D,Transactions!$C:$C,$U11,Transactions!$A:$A,">="&DATE(Dashboard!$B$5,5,1),Transactions!$A:$A,"<"&DATE(Dashboard!$B$5,6,1)) | G11: =SUMIFS(Transactions!$D:$D,Transactions!$C:$C,$U11,Transactions!$A:$A,">="&DATE(Dashboard!$B$5,6,1),Transactions!$A:$A,"<"&DATE(Dashboard!$B$5,7,1)) | H11: =SUMIFS(Transactions!$D:$D,Transactions!$C:$C,$U11,Transactions!$A:$A,">="&DATE(Dashboard!$B$5,7,1),Transactions!$A:$A,"<"&DATE(Dashboard!$B$5,8,1)) | I11: =SUMIFS(Transactions!$D:$D,Transactions!$C:$C,$U11,Transactions!$A:$A,">="&DATE(Dashboard!$B$5,8,1),Transactions!$A:$A,"<"&DATE(Dashboard!$B$5,9,1)) | J11: =SUMIFS(Transactions!$D:$D,Transactions!$C:$C,$U11,Transactions!$A:$A,">="&DATE(Dashboard!$B$5,9,1),Transactions!$A:$A,"<"&DATE(Dashboard!$B$5,10,1)) | K11: =SUMIFS(Transactions!$D:$D,Transactions!$C:$C,$U11,Transactions!$A:$A,">="&DATE(Dashboard!$B$5,10,1),Transactions!$A:$A,"<"&DATE(Dashboard!$B$5,11,1)) | L11: =SUMIFS(Transactions!$D:$D,Transactions!$C:$C,$U11,Transactions!$A:$A,">="&DATE(Dashboard!$B$5,11,1),Transactions!$A:$A,"<"&DATE(Dashboard!$B$5,12,1)) | M11: =SUMIFS(Transactions!$D:$D,Transactions!$C:$C,$U11,Transactions!$A:$A,">="&DATE(Dashboard!$B$5,12,1),Transactions!$A:$A,"<"&DATE(Dashboard!$B$5,13,1)) | N11: =SUM(B11:M11) | O11: =Budget!D11 | P11: =ROUND(O11-N11,2) | Q11: =IF(O11=0,"",N11/O11) | R11: =Budget!C11 | S11: =IF(ISNUMBER(Dashboard!$F$5),INDEX(B11:M11,1,MONTH(Dashboard!$F$5)),0) | T11: =ROUND(R11-S11,2) | U11: =SUBSTITUTE(SUBSTITUTE(SUBSTITUTE($A11,"~","~~"),"*","~*"),"?","~?")
A12: =IF(Budget!A12="","(unused)",Budget!A12) | B12: =SUMIFS(Transactions!$D:$D,Transactions!$C:$C,$U12,Transactions!$A:$A,">="&DATE(Dashboard!$B$5,1,1),Transactions!$A:$A,"<"&DATE(Dashboard!$B$5,2,1)) | C12: =SUMIFS(Transactions!$D:$D,Transactions!$C:$C,$U12,Transactions!$A:$A,">="&DATE(Dashboard!$B$5,2,1),Transactions!$A:$A,"<"&DATE(Dashboard!$B$5,3,1)) | D12: =SUMIFS(Transactions!$D:$D,Transactions!$C:$C,$U12,Transactions!$A:$A,">="&DATE(Dashboard!$B$5,3,1),Transactions!$A:$A,"<"&DATE(Dashboard!$B$5,4,1)) | E12: =SUMIFS(Transactions!$D:$D,Transactions!$C:$C,$U12,Transactions!$A:$A,">="&DATE(Dashboard!$B$5,4,1),Transactions!$A:$A,"<"&DATE(Dashboard!$B$5,5,1)) | F12: =SUMIFS(Transactions!$D:$D,Transactions!$C:$C,$U12,Transactions!$A:$A,">="&DATE(Dashboard!$B$5,5,1),Transactions!$A:$A,"<"&DATE(Dashboard!$B$5,6,1)) | G12: =SUMIFS(Transactions!$D:$D,Transactions!$C:$C,$U12,Transactions!$A:$A,">="&DATE(Dashboard!$B$5,6,1),Transactions!$A:$A,"<"&DATE(Dashboard!$B$5,7,1)) | H12: =SUMIFS(Transactions!$D:$D,Transactions!$C:$C,$U12,Transactions!$A:$A,">="&DATE(Dashboard!$B$5,7,1),Transactions!$A:$A,"<"&DATE(Dashboard!$B$5,8,1)) | I12: =SUMIFS(Transactions!$D:$D,Transactions!$C:$C,$U12,Transactions!$A:$A,">="&DATE(Dashboard!$B$5,8,1),Transactions!$A:$A,"<"&DATE(Dashboard!$B$5,9,1)) | J12: =SUMIFS(Transactions!$D:$D,Transactions!$C:$C,$U12,Transactions!$A:$A,">="&DATE(Dashboard!$B$5,9,1),Transactions!$A:$A,"<"&DATE(Dashboard!$B$5,10,1)) | K12: =SUMIFS(Transactions!$D:$D,Transactions!$C:$C,$U12,Transactions!$A:$A,">="&DATE(Dashboard!$B$5,10,1),Transactions!$A:$A,"<"&DATE(Dashboard!$B$5,11,1)) | L12: =SUMIFS(Transactions!$D:$D,Transactions!$C:$C,$U12,Transactions!$A:$A,">="&DATE(Dashboard!$B$5,11,1),Transactions!$A:$A,"<"&DATE(Dashboard!$B$5,12,1)) | M12: =SUMIFS(Transactions!$D:$D,Transactions!$C:$C,$U12,Transactions!$A:$A,">="&DATE(Dashboard!$B$5,12,1),Transactions!$A:$A,"<"&DATE(Dashboard!$B$5,13,1)) | N12: =SUM(B12:M12) | O12: =Budget!D12 | P12: =ROUND(O12-N12,2) | Q12: =IF(O12=0,"",N12/O12) | R12: =Budget!C12 | S12: =IF(ISNUMBER(Dashboard!$F$5),INDEX(B12:M12,1,MONTH(Dashboard!$F$5)),0) | T12: =ROUND(R12-S12,2) | U12: =SUBSTITUTE(SUBSTITUTE(SUBSTITUTE($A12,"~","~~"),"*","~*"),"?","~?")
A13: =IF(Budget!A13="","(unused)",Budget!A13) | B13: =SUMIFS(Transactions!$D:$D,Transactions!$C:$C,$U13,Transactions!$A:$A,">="&DATE(Dashboard!$B$5,1,1),Transactions!$A:$A,"<"&DATE(Dashboard!$B$5,2,1)) | C13: =SUMIFS(Transactions!$D:$D,Transactions!$C:$C,$U13,Transactions!$A:$A,">="&DATE(Dashboard!$B$5,2,1),Transactions!$A:$A,"<"&DATE(Dashboard!$B$5,3,1)) | D13: =SUMIFS(Transactions!$D:$D,Transactions!$C:$C,$U13,Transactions!$A:$A,">="&DATE(Dashboard!$B$5,3,1),Transactions!$A:$A,"<"&DATE(Dashboard!$B$5,4,1)) | E13: =SUMIFS(Transactions!$D:$D,Transactions!$C:$C,$U13,Transactions!$A:$A,">="&DATE(Dashboard!$B$5,4,1),Transactions!$A:$A,"<"&DATE(Dashboard!$B$5,5,1)) | F13: =SUMIFS(Transactions!$D:$D,Transactions!$C:$C,$U13,Transactions!$A:$A,">="&DATE(Dashboard!$B$5,5,1),Transactions!$A:$A,"<"&DATE(Dashboard!$B$5,6,1)) | G13: =SUMIFS(Transactions!$D:$D,Transactions!$C:$C,$U13,Transactions!$A:$A,">="&DATE(Dashboard!$B$5,6,1),Transactions!$A:$A,"<"&DATE(Dashboard!$B$5,7,1)) | H13: =SUMIFS(Transactions!$D:$D,Transactions!$C:$C,$U13,Transactions!$A:$A,">="&DATE(Dashboard!$B$5,7,1),Transactions!$A:$A,"<"&DATE(Dashboard!$B$5,8,1)) | I13: =SUMIFS(Transactions!$D:$D,Transactions!$C:$C,$U13,Transactions!$A:$A,">="&DATE(Dashboard!$B$5,8,1),Transactions!$A:$A,"<"&DATE(Dashboard!$B$5,9,1)) | J13: =SUMIFS(Transactions!$D:$D,Transactions!$C:$C,$U13,Transactions!$A:$A,">="&DATE(Dashboard!$B$5,9,1),Transactions!$A:$A,"<"&DATE(Dashboard!$B$5,10,1)) | K13: =SUMIFS(Transactions!$D:$D,Transactions!$C:$C,$U13,Transactions!$A:$A,">="&DATE(Dashboard!$B$5,10,1),Transactions!$A:$A,"<"&DATE(Dashboard!$B$5,11,1)) | L13: =SUMIFS(Transactions!$D:$D,Transactions!$C:$C,$U13,Transactions!$A:$A,">="&DATE(Dashboard!$B$5,11,1),Transactions!$A:$A,"<"&DATE(Dashboard!$B$5,12,1)) | M13: =SUMIFS(Transactions!$D:$D,Transactions!$C:$C,$U13,Transactions!$A:$A,">="&DATE(Dashboard!$B$5,12,1),Transactions!$A:$A,"<"&DATE(Dashboard!$B$5,13,1)) | N13: =SUM(B13:M13) | O13: =Budget!D13 | P13: =ROUND(O13-N13,2) | Q13: =IF(O13=0,"",N13/O13) | R13: =Budget!C13 | S13: =IF(ISNUMBER(Dashboard!$F$5),INDEX(B13:M13,1,MONTH(Dashboard!$F$5)),0) | T13: =ROUND(R13-S13,2) | U13: =SUBSTITUTE(SUBSTITUTE(SUBSTITUTE($A13,"~","~~"),"*","~*"),"?","~?")
... A15: =IF(Budget!A15="","(unused)",Budget!A15) | B15: =SUMIFS(Transactions!$D:$D,Transactions!$C:$C,$U15,Transactions!$A:$A,">="&DATE(Dashboard!$B$5,1,1),Transactions!$A:$A,"<"&DATE(Dashboard!$B$5,2,1)) | C15: =SUMIFS(Transactions!$D:$D,Transactions!$C:$C,$U15,Transactions!$A:$A,">="&DATE(Dashboard!$B$5,2,1),Transactions!$A:$A,"<"&DATE(Dashboard!$B$5,3,1)) | D15: =SUMIFS(Transactions!$D:$D,Transactions!$C:$C,$U15,Transactions!$A:$A,">="&DATE(Dashboard!$B$5,3,1),Transactions!$A:$A,"<"&DATE(Dashboard!$B$5,4,1)) | E15: =SUMIFS(Transactions!$D:$D,Transactions!$C:$C,$U15,Transactions!$A:$A,">="&DATE(Dashboard!$B$5,4,1),Transactions!$A:$A,"<"&DATE(Dashboard!$B$5,5,1)) | F15: =SUMIFS(Transactions!$D:$D,Transactions!$C:$C,$U15,Transactions!$A:$A,">="&DATE(Dashboard!$B$5,5,1),Transactions!$A:$A,"<"&DATE(Dashboard!$B$5,6,1)) | G15: =SUMIFS(Transactions!$D:$D,Transactions!$C:$C,$U15,Transactions!$A:$A,">="&DATE(Dashboard!$B$5,6,1),Transactions!$A:$A,"<"&DATE(Dashboard!$B$5,7,1)) | H15: =SUMIFS(Transactions!$D:$D,Transactions!$C:$C,$U15,Transactions!$A:$A,">="&DATE(Dashboard!$B$5,7,1),Transactions!$A:$A,"<"&DATE(Dashboard!$B$5,8,1)) | I15: =SUMIFS(Transactions!$D:$D,Transactions!$C:$C,$U15,Transactions!$A:$A,">="&DATE(Dashboard!$B$5,8,1),Transactions!$A:$A,"<"&DATE(Dashboard!$B$5,9,1)) | J15: =SUMIFS(Transactions!$D:$D,Transactions!$C:$C,$U15,Transactions!$A:$A,">="&DATE(Dashboard!$B$5,9,1),Transactions!$A:$A,"<"&DATE(Dashboard!$B$5,10,1)) | K15: =SUMIFS(Transactions!$D:$D,Transactions!$C:$C,$U15,Transactions!$A:$A,">="&DATE(Dashboard!$B$5,10,1),Transactions!$A:$A,"<"&DATE(Dashboard!$B$5,11,1)) | L15: =SUMIFS(Transactions!$D:$D,Transactions!$C:$C,$U15,Transactions!$A:$A,">="&DATE(Dashboard!$B$5,11,1),Transactions!$A:$A,"<"&DATE(Dashboard!$B$5,12,1)) | M15: =SUMIFS(Transactions!$D:$D,Transactions!$C:$C,$U15,Transactions!$A:$A,">="&DATE(Dashboard!$B$5,12,1),Transactions!$A:$A,"<"&DATE(Dashboard!$B$5,13,1)) | N15: =SUM(B15:M15) | O15: =Budget!D15 | P15: =ROUND(O15-N15,2) | Q15: =IF(O15=0,"",N15/O15) | R15: =Budget!C15 | S15: =IF(ISNUMBER(Dashboard!$F$5),INDEX(B15:M15,1,MONTH(Dashboard!$F$5)),0) | T15: =ROUND(R15-S15,2) | U15: =SUBSTITUTE(SUBSTITUTE(SUBSTITUTE($A15,"~","~~"),"*","~*"),"?","~?")
A17: Total spent | B17: =SUM(B2:B13) | C17: =SUM(C2:C13) | D17: =SUM(D2:D13) | E17: =SUM(E2:E13) | F17: =SUM(F2:F13) | G17: =SUM(G2:G13) | H17: =SUM(H2:H13) | I17: =SUM(I2:I13) | ... O17: =SUM(O2:O13) | P17: =ROUND(O17-N17,2) | Q17: =IF(O17=0,"",N17/O17) | R17: =SUM(R2:R13) | S17: =SUM(S2:S13) | T17: =ROUND(R17-S17,2)
A18: Total income | B18: =SUM(B14:B15) | C18: =SUM(C14:C15) | D18: =SUM(D14:D15) | E18: =SUM(E14:E15) | F18: =SUM(F14:F15) | G18: =SUM(G14:G15) | H18: =SUM(H14:H15) | I18: =SUM(I14:I15) | ... O18: =SUM(O14:O15) | P18: =ROUND(O18-N18,2) | Q18: =IF(O18=0,"",N18/O18) | R18: =SUM(R14:R15) | S18: =SUM(S14:S15) | T18: =ROUND(R18-S18,2)
A19: Net saved | B19: =ROUND(B18-B17,2) | C19: =ROUND(C18-C17,2) | D19: =ROUND(D18-D17,2) | E19: =ROUND(E18-E17,2) | F19: =ROUND(F18-F17,2) | G19: =ROUND(G18-G17,2) | H19: =ROUND(H18-H17,2) | I19: =ROUND(I18-I17,2) | ... O19: =ROUND(O18-O17,2) | R19: =ROUND(R18-R17,2) | S19: =ROUND(S18-S17,2)
A20: Check: uncategorized | B20: =ROUND(SUMIFS(Transactions!$D:$D,Transactions!$A:$A,">="&DATE(Dashboard!$B$5,1,1),Transactions!$A:$A,"<"&DATE(Dashboard!$B$5,2,1))-B17-B18,2) | C20: =ROUND(SUMIFS(Transactions!$D:$D,Transactions!$A:$A,">="&DATE(Dashboard!$B$5,2,1),Transactions!$A:$A,"<"&DATE(Dashboard!$B$5,3,1))-C17-C18,2) | D20: =ROUND(SUMIFS(Transactions!$D:$D,Transactions!$A:$A,">="&DATE(Dashboard!$B$5,3,1),Transactions!$A:$A,"<"&DATE(Dashboard!$B$5,4,1))-D17-D18,2) | E20: =ROUND(SUMIFS(Transactions!$D:$D,Transactions!$A:$A,">="&DATE(Dashboard!$B$5,4,1),Transactions!$A:$A,"<"&DATE(Dashboard!$B$5,5,1))-E17-E18,2) | F20: =ROUND(SUMIFS(Transactions!$D:$D,Transactions!$A:$A,">="&DATE(Dashboard!$B$5,5,1),Transactions!$A:$A,"<"&DATE(Dashboard!$B$5,6,1))-F17-F18,2) | G20: =ROUND(SUMIFS(Transactions!$D:$D,Transactions!$A:$A,">="&DATE(Dashboard!$B$5,6,1),Transactions!$A:$A,"<"&DATE(Dashboard!$B$5,7,1))-G17-G18,2) | H20: =ROUND(SUMIFS(Transactions!$D:$D,Transactions!$A:$A,">="&DATE(Dashboard!$B$5,7,1),Transactions!$A:$A,"<"&DATE(Dashboard!$B$5,8,1))-H17-H18,2) | I20: =ROUND(SUMIFS(Transactions!$D:$D,Transactions!$A:$A,">="&DATE(Dashboard!$B$5,8,1),Transactions!$A:$A,"<"&DATE(Dashboard!$B$5,9,1))-I17-I18,2) | J20: =ROUND(SUMIFS(Transactions!$D:$D,Transactions!$A:$A,">="&DATE(Dashboard!$B$5,9,1),Transactions!$A:$A,"<"&DATE(Dashboard!$B$5,10,1))-J17-J18,2) | K20: =ROUND(SUMIFS(Transactions!$D:$D,Transactions!$A:$A,">="&DATE(Dashboard!$B$5,10,1),Transactions!$A:$A,"<"&DATE(Dashboard!$B$5,11,1))-K17-K18,2) | L20: =ROUND(SUMIFS(Transactions!$D:$D,Transactions!$A:$A,">="&DATE(Dashboard!$B$5,11,1),Transactions!$A:$A,"<"&DATE(Dashboard!$B$5,12,1))-L17-L18,2) | M20: =ROUND(SUMIFS(Transactions!$D:$D,Transactions!$A:$A,">="&DATE(Dashboard!$B$5,12,1),Transactions!$A:$A,"<"&DATE(Dashboard!$B$5,13,1))-M17-M18,2) | N20: =ROUND(SUMPRODUCT(ABS(B20:M20)),2)
A21: Check: missing data | B21: =SUMPRODUCT((LEN(Transactions!$C$2:$C$10000&Transactions!$D$2:$D$10000)>0)*(ISNUMBER(Transactions!$A$2:$A$10000)*ISNUMBER(Transactions!$D$2:$D$10000)=0))
A22: Month | B22: Income | C22: Spent | D22: Net Saved
A23: Jan | B23: =B18 | C23: =B17 | D23: =ROUND(B23-C23,2)
A24: Feb | B24: =C18 | C24: =C17 | D24: =ROUND(B24-C24,2)
A25: Mar | B25: =D18 | C25: =D17 | D25: =ROUND(B25-C25,2)
A26: Apr | B26: =E18 | C26: =E17 | D26: =ROUND(B26-C26,2)
A27: May | B27: =F18 | C27: =F17 | D27: =ROUND(B27-C27,2)
A28: Jun | B28: =G18 | C28: =G17 | D28: =ROUND(B28-C28,2)
A29: Jul | B29: =H18 | C29: =H17 | D29: =ROUND(B29-C29,2)
A30: Aug | B30: =I18 | C30: =I17 | D30: =ROUND(B30-C30,2)
A31: Sep | B31: =J18 | C31: =J17 | D31: =ROUND(B31-C31,2)
A32: Oct | B32: =K18 | C32: =K17 | D32: =ROUND(B32-C32,2)
A33: Nov | B33: =L18 | C33: =L17 | D33: =ROUND(B33-C33,2)
A34: Dec | B34: =M18 | C34: =M17 | D34: =ROUND(B34-C34,2)
A35: Total | B35: =SUM(B23:B34) | C35: =SUM(C23:C34) | D35: =ROUND(B35-C35,2)
A37: The year and the Month columns (R-T) follow the Year and Month picked on the Dashboard.
A38: Check: uncategorized should be 0. It is money logged that month whose Category isn't on the Budget list (a negative number means something is counted twice, e.g. two categories with the same name).
A39: Check: missing data should be 0. It counts rows whose Date or Amount is blank or isn't a real date/number.
