Workbook

Sheet Start Here
B2: B U D G E T B Y P A Y C H E C K
B4: YOUR PAYDAYS
B5: First payday (type your own date here) | C5: =DATE(2026,10,9)
B6: Last payday in this tracker | C6: =IF(AND(ISNUMBER(C5),C5>=DATE(2000,1,1)),MAX(Paychecks!$B$2:$B$27),"")
B7: Extra paychecks in this window (3rd payday in a month) | C7: =IF(AND(ISNUMBER(C5),C5>=DATE(2000,1,1)),COUNTIF(Paychecks!$C$2:$C$27,3),"")
B9: HOW TO USE
B10: 1. Set your first payday above; the other 25 paydays fill in every 14 days.
B11: 2. Bills tab: list each monthly bill with its category, due day and amount.
B12: 3. Tag each bill 1 or 2, the paycheck that arrives before it's due:
B13: 1 = first payday of the month (1st-14th), 2 = second payday (15th-28th).
B14: Bills due the 1st-14th usually come out of the previous month's check 2.
B15: A 3rd payday in a month is an extra paycheck: no bills come out of it.
B16: 4. Paychecks tab: yellow cells are yours. Enter Take-Home Pay and Savings in dollars,
B17: and log what you actually spend in Spent as each pay period goes by.
B18: 5. Red cells flag something to fix. Keep the # column as is: it sets each date.
B19: 6. Dashboard tab: totals for all 26 paychecks and your monthly bills by category.

Sheet Bills
A1: Bill | B1: Category | C1: Due Day | D1: Monthly Amount | E1: Paid From Check #
A2: Rent | B2: Housing | C2: 1 | D2: 1300 | E2: 2
A3: Internet | B3: Phone & Internet | C3: 5 | D3: 70 | E3: 2
A4: Streaming services | B4: Subscriptions | C4: 8 | D4: 25 | E4: 2
A5: Student loan | B5: Debt | C5: 10 | D5: 180 | E5: 2
A6: Car payment | B6: Transportation | C6: 15 | D6: 340 | E6: 1
A7: Electric | B7: Utilities | C7: 18 | D7: 110 | E7: 1
A8: Phone | B8: Phone & Internet | C8: 20 | D8: 65 | E8: 1
A9: Water & trash | B9: Utilities | C9: 22 | D9: 55 | E9: 1
A10: Car insurance | B10: Insurance | C10: 25 | D10: 145 | E10: 1
A11: Credit card | B11: Debt | C11: 28 | D11: 150 | E11: 1
A12: Gym | B12: Subscriptions | C12: 28 | D12: 35 | E12: 1

Sheet Paychecks
A1: # | B1: Payday | C1: Check # in Month | D1: Take-Home Pay | E1: Bills Due | F1: Savings | G1: Left to Spend | H1: Spent | I1: Remaining | J1: Note
A2: 1 | B2: =IF(AND(ISNUMBER('Start Here'!$C$5),'Start Here'!$C$5>=DATE(2000,1,1)),'Start Here'!$C$5+14*(A2-1),"") | C2: =IF(B2="","",INT((DAY(B2)-1)/14)+1) | D2: 2250 | E2: =IF(OR(C2="",C2=3),0,SUMIF(Bills!$E:$E,C2,Bills!$D:$D)) | F2: 150 | G2: =IF(ISNUMBER(D2),D2,0)-E2-IF(ISNUMBER(F2),F2,0) | I2: =IF(H2="","",IF(ISNUMBER(H2),ROUND(G2-H2,2),"Not a number")) | J2: =IF(B2="","Set your first payday on Start Here",IF(D2="","Enter take-home pay",IF(OR(NOT(ISNUMBER(D2)),D2<0,AND(F2<>"",NOT(ISNUMBER(F2))),AND(ISNUMBER(F2),F2<0)),"Pay and savings must be numbers, not text or negatives",IF(ROUND(G2,2)<0,"Short: bills + savings exceed pay",IF(C2=3,"Extra paycheck: no bills due","")))))
A3: 2 | B3: =IF(AND(ISNUMBER('Start Here'!$C$5),'Start Here'!$C$5>=DATE(2000,1,1)),'Start Here'!$C$5+14*(A3-1),"") | C3: =IF(B3="","",INT((DAY(B3)-1)/14)+1) | D3: 2250 | E3: =IF(OR(C3="",C3=3),0,SUMIF(Bills!$E:$E,C3,Bills!$D:$D)) | F3: 150 | G3: =IF(ISNUMBER(D3),D3,0)-E3-IF(ISNUMBER(F3),F3,0) | I3: =IF(H3="","",IF(ISNUMBER(H3),ROUND(G3-H3,2),"Not a number")) | J3: =IF(B3="","Set your first payday on Start Here",IF(D3="","Enter take-home pay",IF(OR(NOT(ISNUMBER(D3)),D3<0,AND(F3<>"",NOT(ISNUMBER(F3))),AND(ISNUMBER(F3),F3<0)),"Pay and savings must be numbers, not text or negatives",IF(ROUND(G3,2)<0,"Short: bills + savings exceed pay",IF(C3=3,"Extra paycheck: no bills due","")))))
A4: 3 | B4: =IF(AND(ISNUMBER('Start Here'!$C$5),'Start Here'!$C$5>=DATE(2000,1,1)),'Start Here'!$C$5+14*(A4-1),"") | C4: =IF(B4="","",INT((DAY(B4)-1)/14)+1) | D4: 2250 | E4: =IF(OR(C4="",C4=3),0,SUMIF(Bills!$E:$E,C4,Bills!$D:$D)) | F4: 150 | G4: =IF(ISNUMBER(D4),D4,0)-E4-IF(ISNUMBER(F4),F4,0) | I4: =IF(H4="","",IF(ISNUMBER(H4),ROUND(G4-H4,2),"Not a number")) | J4: =IF(B4="","Set your first payday on Start Here",IF(D4="","Enter take-home pay",IF(OR(NOT(ISNUMBER(D4)),D4<0,AND(F4<>"",NOT(ISNUMBER(F4))),AND(ISNUMBER(F4),F4<0)),"Pay and savings must be numbers, not text or negatives",IF(ROUND(G4,2)<0,"Short: bills + savings exceed pay",IF(C4=3,"Extra paycheck: no bills due","")))))
A5: 4 | B5: =IF(AND(ISNUMBER('Start Here'!$C$5),'Start Here'!$C$5>=DATE(2000,1,1)),'Start Here'!$C$5+14*(A5-1),"") | C5: =IF(B5="","",INT((DAY(B5)-1)/14)+1) | D5: 2250 | E5: =IF(OR(C5="",C5=3),0,SUMIF(Bills!$E:$E,C5,Bills!$D:$D)) | F5: 150 | G5: =IF(ISNUMBER(D5),D5,0)-E5-IF(ISNUMBER(F5),F5,0) | I5: =IF(H5="","",IF(ISNUMBER(H5),ROUND(G5-H5,2),"Not a number")) | J5: =IF(B5="","Set your first payday on Start Here",IF(D5="","Enter take-home pay",IF(OR(NOT(ISNUMBER(D5)),D5<0,AND(F5<>"",NOT(ISNUMBER(F5))),AND(ISNUMBER(F5),F5<0)),"Pay and savings must be numbers, not text or negatives",IF(ROUND(G5,2)<0,"Short: bills + savings exceed pay",IF(C5=3,"Extra paycheck: no bills due","")))))
A6: 5 | B6: =IF(AND(ISNUMBER('Start Here'!$C$5),'Start Here'!$C$5>=DATE(2000,1,1)),'Start Here'!$C$5+14*(A6-1),"") | C6: =IF(B6="","",INT((DAY(B6)-1)/14)+1) | D6: 2250 | E6: =IF(OR(C6="",C6=3),0,SUMIF(Bills!$E:$E,C6,Bills!$D:$D)) | F6: 150 | G6: =IF(ISNUMBER(D6),D6,0)-E6-IF(ISNUMBER(F6),F6,0) | I6: =IF(H6="","",IF(ISNUMBER(H6),ROUND(G6-H6,2),"Not a number")) | J6: =IF(B6="","Set your first payday on Start Here",IF(D6="","Enter take-home pay",IF(OR(NOT(ISNUMBER(D6)),D6<0,AND(F6<>"",NOT(ISNUMBER(F6))),AND(ISNUMBER(F6),F6<0)),"Pay and savings must be numbers, not text or negatives",IF(ROUND(G6,2)<0,"Short: bills + savings exceed pay",IF(C6=3,"Extra paycheck: no bills due","")))))
A7: 6 | B7: =IF(AND(ISNUMBER('Start Here'!$C$5),'Start Here'!$C$5>=DATE(2000,1,1)),'Start Here'!$C$5+14*(A7-1),"") | C7: =IF(B7="","",INT((DAY(B7)-1)/14)+1) | D7: 2250 | E7: =IF(OR(C7="",C7=3),0,SUMIF(Bills!$E:$E,C7,Bills!$D:$D)) | F7: 150 | G7: =IF(ISNUMBER(D7),D7,0)-E7-IF(ISNUMBER(F7),F7,0) | I7: =IF(H7="","",IF(ISNUMBER(H7),ROUND(G7-H7,2),"Not a number")) | J7: =IF(B7="","Set your first payday on Start Here",IF(D7="","Enter take-home pay",IF(OR(NOT(ISNUMBER(D7)),D7<0,AND(F7<>"",NOT(ISNUMBER(F7))),AND(ISNUMBER(F7),F7<0)),"Pay and savings must be numbers, not text or negatives",IF(ROUND(G7,2)<0,"Short: bills + savings exceed pay",IF(C7=3,"Extra paycheck: no bills due","")))))
A8: 7 | B8: =IF(AND(ISNUMBER('Start Here'!$C$5),'Start Here'!$C$5>=DATE(2000,1,1)),'Start Here'!$C$5+14*(A8-1),"") | C8: =IF(B8="","",INT((DAY(B8)-1)/14)+1) | D8: 2250 | E8: =IF(OR(C8="",C8=3),0,SUMIF(Bills!$E:$E,C8,Bills!$D:$D)) | F8: 150 | G8: =IF(ISNUMBER(D8),D8,0)-E8-IF(ISNUMBER(F8),F8,0) | I8: =IF(H8="","",IF(ISNUMBER(H8),ROUND(G8-H8,2),"Not a number")) | J8: =IF(B8="","Set your first payday on Start Here",IF(D8="","Enter take-home pay",IF(OR(NOT(ISNUMBER(D8)),D8<0,AND(F8<>"",NOT(ISNUMBER(F8))),AND(ISNUMBER(F8),F8<0)),"Pay and savings must be numbers, not text or negatives",IF(ROUND(G8,2)<0,"Short: bills + savings exceed pay",IF(C8=3,"Extra paycheck: no bills due","")))))
A9: 8 | B9: =IF(AND(ISNUMBER('Start Here'!$C$5),'Start Here'!$C$5>=DATE(2000,1,1)),'Start Here'!$C$5+14*(A9-1),"") | C9: =IF(B9="","",INT((DAY(B9)-1)/14)+1) | D9: 2250 | E9: =IF(OR(C9="",C9=3),0,SUMIF(Bills!$E:$E,C9,Bills!$D:$D)) | F9: 150 | G9: =IF(ISNUMBER(D9),D9,0)-E9-IF(ISNUMBER(F9),F9,0) | I9: =IF(H9="","",IF(ISNUMBER(H9),ROUND(G9-H9,2),"Not a number")) | J9: =IF(B9="","Set your first payday on Start Here",IF(D9="","Enter take-home pay",IF(OR(NOT(ISNUMBER(D9)),D9<0,AND(F9<>"",NOT(ISNUMBER(F9))),AND(ISNUMBER(F9),F9<0)),"Pay and savings must be numbers, not text or negatives",IF(ROUND(G9,2)<0,"Short: bills + savings exceed pay",IF(C9=3,"Extra paycheck: no bills due","")))))
A10: 9 | B10: =IF(AND(ISNUMBER('Start Here'!$C$5),'Start Here'!$C$5>=DATE(2000,1,1)),'Start Here'!$C$5+14*(A10-1),"") | C10: =IF(B10="","",INT((DAY(B10)-1)/14)+1) | D10: 2250 | E10: =IF(OR(C10="",C10=3),0,SUMIF(Bills!$E:$E,C10,Bills!$D:$D)) | F10: 150 | G10: =IF(ISNUMBER(D10),D10,0)-E10-IF(ISNUMBER(F10),F10,0) | I10: =IF(H10="","",IF(ISNUMBER(H10),ROUND(G10-H10,2),"Not a number")) | J10: =IF(B10="","Set your first payday on Start Here",IF(D10="","Enter take-home pay",IF(OR(NOT(ISNUMBER(D10)),D10<0,AND(F10<>"",NOT(ISNUMBER(F10))),AND(ISNUMBER(F10),F10<0)),"Pay and savings must be numbers, not text or negatives",IF(ROUND(G10,2)<0,"Short: bills + savings exceed pay",IF(C10=3,"Extra paycheck: no bills due","")))))
A11: 10 | B11: =IF(AND(ISNUMBER('Start Here'!$C$5),'Start Here'!$C$5>=DATE(2000,1,1)),'Start Here'!$C$5+14*(A11-1),"") | C11: =IF(B11="","",INT((DAY(B11)-1)/14)+1) | D11: 2250 | E11: =IF(OR(C11="",C11=3),0,SUMIF(Bills!$E:$E,C11,Bills!$D:$D)) | F11: 150 | G11: =IF(ISNUMBER(D11),D11,0)-E11-IF(ISNUMBER(F11),F11,0) | I11: =IF(H11="","",IF(ISNUMBER(H11),ROUND(G11-H11,2),"Not a number")) | J11: =IF(B11="","Set your first payday on Start Here",IF(D11="","Enter take-home pay",IF(OR(NOT(ISNUMBER(D11)),D11<0,AND(F11<>"",NOT(ISNUMBER(F11))),AND(ISNUMBER(F11),F11<0)),"Pay and savings must be numbers, not text or negatives",IF(ROUND(G11,2)<0,"Short: bills + savings exceed pay",IF(C11=3,"Extra paycheck: no bills due","")))))
A12: 11 | B12: =IF(AND(ISNUMBER('Start Here'!$C$5),'Start Here'!$C$5>=DATE(2000,1,1)),'Start Here'!$C$5+14*(A12-1),"") | C12: =IF(B12="","",INT((DAY(B12)-1)/14)+1) | D12: 2250 | E12: =IF(OR(C12="",C12=3),0,SUMIF(Bills!$E:$E,C12,Bills!$D:$D)) | F12: 150 | G12: =IF(ISNUMBER(D12),D12,0)-E12-IF(ISNUMBER(F12),F12,0) | I12: =IF(H12="","",IF(ISNUMBER(H12),ROUND(G12-H12,2),"Not a number")) | J12: =IF(B12="","Set your first payday on Start Here",IF(D12="","Enter take-home pay",IF(OR(NOT(ISNUMBER(D12)),D12<0,AND(F12<>"",NOT(ISNUMBER(F12))),AND(ISNUMBER(F12),F12<0)),"Pay and savings must be numbers, not text or negatives",IF(ROUND(G12,2)<0,"Short: bills + savings exceed pay",IF(C12=3,"Extra paycheck: no bills due","")))))
A13: 12 | B13: =IF(AND(ISNUMBER('Start Here'!$C$5),'Start Here'!$C$5>=DATE(2000,1,1)),'Start Here'!$C$5+14*(A13-1),"") | C13: =IF(B13="","",INT((DAY(B13)-1)/14)+1) | D13: 2250 | E13: =IF(OR(C13="",C13=3),0,SUMIF(Bills!$E:$E,C13,Bills!$D:$D)) | F13: 150 | G13: =IF(ISNUMBER(D13),D13,0)-E13-IF(ISNUMBER(F13),F13,0) | I13: =IF(H13="","",IF(ISNUMBER(H13),ROUND(G13-H13,2),"Not a number")) | J13: =IF(B13="","Set your first payday on Start Here",IF(D13="","Enter take-home pay",IF(OR(NOT(ISNUMBER(D13)),D13<0,AND(F13<>"",NOT(ISNUMBER(F13))),AND(ISNUMBER(F13),F13<0)),"Pay and savings must be numbers, not text or negatives",IF(ROUND(G13,2)<0,"Short: bills + savings exceed pay",IF(C13=3,"Extra paycheck: no bills due","")))))
... A27: 26 | B27: =IF(AND(ISNUMBER('Start Here'!$C$5),'Start Here'!$C$5>=DATE(2000,1,1)),'Start Here'!$C$5+14*(A27-1),"") | C27: =IF(B27="","",INT((DAY(B27)-1)/14)+1) | D27: 2250 | E27: =IF(OR(C27="",C27=3),0,SUMIF(Bills!$E:$E,C27,Bills!$D:$D)) | F27: 150 | G27: =IF(ISNUMBER(D27),D27,0)-E27-IF(ISNUMBER(F27),F27,0) | I27: =IF(H27="","",IF(ISNUMBER(H27),ROUND(G27-H27,2),"Not a number")) | J27: =IF(B27="","Set your first payday on Start Here",IF(D27="","Enter take-home pay",IF(OR(NOT(ISNUMBER(D27)),D27<0,AND(F27<>"",NOT(ISNUMBER(F27))),AND(ISNUMBER(F27),F27<0)),"Pay and savings must be numbers, not text or negatives",IF(ROUND(G27,2)<0,"Short: bills + savings exceed pay",IF(C27=3,"Extra paycheck: no bills due","")))))

Sheet Dashboard
B2: 2 6 P A Y C H E C K S A T A G L A N C E
B4: TAKE-HOME PAY | E4: BILLS | H4: SAVINGS | K4: LEFT TO SPEND
B5: =SUM(Paychecks!D2:D27) | E5: =SUM(Paychecks!E2:E27) | H5: =SUM(Paychecks!F2:F27) | K5: =SUM(Paychecks!G2:G27)
B7: =IF(NOT(AND(ISNUMBER('Start Here'!$C$5),'Start Here'!$C$5>=DATE(2000,1,1))),"Set your first payday on Start Here: no bills are scheduled until you do.",IF(OR(F40<>0,F41<>0),"Check the Bills tab: a bill has no 1/2 tag or a non-number amount, so it's left out of these totals.",IF(COUNTA(Paychecks!$D$2:$D$27,Paychecks!$F$2:$F$27)-COUNT(Paychecks!$D$2:$D$27,Paychecks!$F$2:$F$27)>0,"Check the Paychecks tab: a pay or savings entry isn't a number, so it's left out of these totals.","")))
B8: P A Y V S . B I L L S B Y P A Y C H E C K #
B26: M O N T H L Y B I L L S
B28: Housing | F28: =SUMIF(Bills!$B:$B,B28,Bills!$D:$D)
B29: Transportation | F29: =SUMIF(Bills!$B:$B,B29,Bills!$D:$D)
B30: Debt | F30: =SUMIF(Bills!$B:$B,B30,Bills!$D:$D)
B31: Utilities | F31: =SUMIF(Bills!$B:$B,B31,Bills!$D:$D)
B32: Insurance | F32: =SUMIF(Bills!$B:$B,B32,Bills!$D:$D)
B33: Phone & Internet | F33: =SUMIF(Bills!$B:$B,B33,Bills!$D:$D)
B34: Subscriptions | F34: =SUMIF(Bills!$B:$B,B34,Bills!$D:$D)
B35: Other / not listed | F35: =ROUND(SUM(Bills!$D:$D)-SUM(F28:F34),2)
B36: Total | F36: =SUM(F28:F35)
B38: Paid from check 1 | F38: =SUMIF(Bills!$E:$E,1,Bills!$D:$D)
B39: Paid from check 2 | F39: =SUMIF(Bills!$E:$E,2,Bills!$D:$D)
B40: Not tagged 1 or 2 (should be $0) | F40: =ROUND(SUM(Bills!$D:$D)-F38-F39,2)
B41: Non-number amounts (should be 0) | F41: =COUNTA(Bills!$D:$D)-COUNT(Bills!$D:$D)-(COUNTA(Bills!$D$1)-COUNT(Bills!$D$1))
